<annotation>
	<folder>resize</folder>
	<filename>license (155).jpg</filename>
	<path>C:\Users\Multimatics\plat_nomor\dataset_mentah\resize\license (155).jpg</path>
	<source>
		<database>Unknown</database>
	</source>
	<size>
		<width>640</width>
		<height>640</height>
		<depth>1</depth>
	</size>
	<segmented>0</segmented>
	<object>
		<name>license</name>
		<pose>Unspecified</pose>
		<truncated>0</truncated>
		<difficult>0</difficult>
		<bndbox>
			<xmin>457</xmin>
			<ymin>118</ymin>
			<xmax>590</xmax>
			<ymax>180</ymax>
		</bndbox>
	</object>
</annotation>